wasp_spotify_bindings/__init__.py
wasp_spotify_bindings/core.py
wasp_spotify_bindings/utils/__init__.py
wasp_spotify_bindings/utils/applescript.py
wasp_spotify_bindings/utils/applescripts.py
wasp_spotify_bindings/utils/lib.py
wasp_spotify_bindings-0.0.1.dist-info/LICENSE
wasp_spotify_bindings-0.0.1.dist-info/METADATA
wasp_spotify_bindings-0.0.1.dist-info/WHEEL
wasp_spotify_bindings-0.0.1.dist-info/top_level.txt
wasp_spotify_bindings-0.0.1.dist-info/RECORD
