Metadata-Version: 2.1
Name: wasp-spotify-bindings
Version: 0.0.1
Summary: Python wrapper to control your Spotify client on MacOS
Home-page: https://github.com/danthelion/wasp
Author: Daniel Palma
Author-email: danivgy@gmail.com
License: UNKNOWN
Keywords: spotify api
Platform: UNKNOWN
